handprint/__init__.py
handprint/__main__.py
handprint/comparison.py
handprint/exceptions.py
handprint/exit_codes.py
handprint/images.py
handprint/main_body.py
handprint/manager.py
handprint/credentials/__init__.py
handprint/credentials/amazon_auth.py
handprint/credentials/base.py
handprint/credentials/credentials_files.py
handprint/credentials/google_auth.py
handprint/credentials/microsoft_auth.py
handprint/services/__init__.py
handprint/services/amazon.py
handprint/services/base.py
handprint/services/google.py
handprint/services/microsoft.py
handprint-1.6.0.dist-info/LICENSE
handprint-1.6.0.dist-info/METADATA
handprint-1.6.0.dist-info/WHEEL
handprint-1.6.0.dist-info/entry_points.txt
handprint-1.6.0.dist-info/top_level.txt
handprint-1.6.0.dist-info/RECORD
